{
	"ulid": "01K1KXTREH9KRR38G1TYEC5Q7Q",
	"minTime": 1753876815155,
	"maxTime": 1754071200000,
	"stats": {
		"numSamples": 3156197,
		"numSeries": 1001,
		"numChunks": 26322
	},
	"compaction": {
		"level": 4,
		"sources": [
			"01K1DXJD7ETEGDP4QEJ37TQMA8",
			"01K1E4E4FD6XD3VT0SYZREP6EZ",
			"01K1EB9VQFDB777XF67S3KQVSN",
			"01K1EJ5JZDG5R6KQ6FRQGY7EX0",
			"01K1ES1A7E97MACMRCS2TETJ0W",
			"01K1EZX1FEN3F4BGVTQY3KT378",
			"01K1F6RRQET96W50ZG71CNN9HZ",
			"01K1FDMFZDBJ1GB78BX4BB6KSA",
			"01K1FMG45PMKC7FGTZ1D8ENASP",
			"01K1FVBVDQCSSPBBGKMH4BCGQE",
			"01K1G27NQHDM0HNYNZ1X01XRQS",
			"01K1G93CZCN93E0C8QZ1GK7SVG",
			"01K1GFZ15PQAF7W19DDPWTS6S1",
			"01K1GPTRDPKVCK7KBCS85R8MYQ",
			"01K1GXPJQFY03KJQQH1EYJZ4YM",
			"01K1H4J9ZETD5ZF20Z7D1141WR",
			"01K1HBE17EGYHNPJK1VED4RQZD",
			"01K1HJ9RFDAG4WNQXX10FEG7WC",
			"01K1HS5FQETP7NDB9JM0EBJX2C",
			"01K1J016ZFDECXX5KA46049AB1",
			"01K1J6WY7F0VVQW2MQJAR6QGN7",
			"01K1JDRNFHE63J1RGRD2EPAEHF",
			"01K1JMMCQD3R2RDAAEFSSGEC7X",
			"01K1JVG0XP506D4M2G348EF9A3",
			"01K1K2BV7FQP97CD1EM3S2Q70W",
			"01K1K97FDQ4YBF05KPGZETVHB2",
			"01K1KG39QERRKXR6CPZ11MKDJ7"
		],
		"parents": [
			{
				"ulid": "01K1G27NXJAMCNKJEPDB9WH9QC",
				"minTime": 1753876815155,
				"maxTime": 1753941600000
			},
			{
				"ulid": "01K1J0175MQY9SZZB53QKRSZFD",
				"minTime": 1753941615155,
				"maxTime": 1754006400000
			},
			{
				"ulid": "01K1KXTRCFX68Q8ZG6FEQGHNFQ",
				"minTime": 1754006415158,
				"maxTime": 1754071200000
			}
		]
	},
	"version": 1
}